[{"id":0,"content":"20||<img src=\"img/bogota.png\">","size":30,"myid":"0","children":[{"id":1,"content":"je suis arrivé en bus et j'ai cherché le premier cybercafé disponible","size":69,"myid":"new"}]},{"id":2,"content":"20||<img src=\"img/envoi.png\">","size":29,"myid":"1"},{"id":3,"content":"20||<img src=\"img/skylineg.jpg\">","size":32,"myid":"2"},{"id":4,"content":"|a|Lundi 11 juin 2012<br>9h35 am UTC (-7)<br>Bogotá, Colombie<br><br><br><br><br><br><h1>“ je suis fatigué, mais je suis arrivé “</h1><br><br><br><br>• localisation: cybercafé de l'aéroport Eldorado<br><br>• température: 29.3°C<br><br>• état émotionnel: stress moyen/faible. fatigue notable du à un mauvais positionnement dans l'avion<br><br>• intervalle de déconnexion: 17 heures 23 minutes<br><br>• note: P. a changé 30 euros au guichet à droite de l'entrée. il s'assied devant un des écrans disponibles, charge la page d'accueil de gmail, et commence à écrire à C.","size":567,"myid":"4","children":[{"id":5,"content":"je suis bien arrivé à 18h<br>prends soin de toi","size":44,"myid":"3","children":[{"id":6,"content":"en t'écrivant, j'ai pensé que ce serait une bonne idée...","size":57,"myid":"6"},{"id":7,"content":"|d|. bien arrivé à Bogotá !<br><br>j'ai pas dormi dans l'avion.<br><br>il y avait un film d'action<br>et le siège a pas voulu être confortable<br><br><br><br><br>il pleut toujours à Paris ?<br><br><br><br>... plus de nouvelles au calme depuis l'hotel<br><br>embrassez-vous de ma part, c'est délicieux<br><br>P.","size":310,"myid":"7","children":[{"id":8,"content":"|c|pas d'avenir","size":15,"myid":"8"},{"id":9,"content":"<img src=\"sk/sc_059.png\">","size":25,"myid":"9","children":[{"id":10,"content":"<img src=\"img/nuves.jpg\">","size":25,"myid":"5"}]},{"id":11,"content":"|c|Combien de temps vais-je rester ici ?","size":40,"myid":"10","children":[{"id":12,"content":"<img src=\"sk/sc_012.png\">","size":25,"myid":"11"}]},{"id":13,"content":"<img src=\"sk/sc_040.png\">","size":25,"myid":"12","children":[{"id":14,"content":"|c|j'ai envie de dormir","size":23,"myid":"13"}]},{"id":15,"content":"|c|je suis parti.<br><br>pour de bon.","size":37,"myid":"14","children":[{"id":16,"content":"|c|c'était sérieux, tout ça ?<br><br>si elle me répond dans l'heure, c'est quelle pense à moi","size":93,"myid":"15"}]},{"id":17,"content":"<img src=\"sk/sc_026.png\">","size":25,"myid":"16","children":[{"id":18,"content":"|c|elle m'oubliera sans doute.<br>je lui donne 2 semaines.","size":58,"myid":"17"}]},{"id":19,"content":"|c|bon. où sont les bus ?","size":25,"myid":"18"}]}]}]}]